odoo/addons/account_sale_stock_report_non_billed/README.rst
odoo/addons/account_sale_stock_report_non_billed/__init__.py
odoo/addons/account_sale_stock_report_non_billed/__manifest__.py
odoo/addons/account_sale_stock_report_non_billed/i18n/account_sale_stock_report_non_billed.pot
odoo/addons/account_sale_stock_report_non_billed/i18n/es.po
odoo/addons/account_sale_stock_report_non_billed/i18n/it.po
odoo/addons/account_sale_stock_report_non_billed/models/__init__.py
odoo/addons/account_sale_stock_report_non_billed/models/account_move_line.py
odoo/addons/account_sale_stock_report_non_billed/models/res_company.py
odoo/addons/account_sale_stock_report_non_billed/models/res_config_settings.py
odoo/addons/account_sale_stock_report_non_billed/models/stock_move.py
odoo/addons/account_sale_stock_report_non_billed/readme/CONTRIBUTORS.md
odoo/addons/account_sale_stock_report_non_billed/readme/DESCRIPTION.md
odoo/addons/account_sale_stock_report_non_billed/readme/USAGE.md
odoo/addons/account_sale_stock_report_non_billed/security/ir.model.access.csv
odoo/addons/account_sale_stock_report_non_billed/static/description/icon.png
odoo/addons/account_sale_stock_report_non_billed/static/description/index.html
odoo/addons/account_sale_stock_report_non_billed/tests/__init__.py
odoo/addons/account_sale_stock_report_non_billed/tests/test_account_sale_stock_report_non_billed.py
odoo/addons/account_sale_stock_report_non_billed/views/res_config_settings_views.xml
odoo/addons/account_sale_stock_report_non_billed/views/stock_move_non_billed_views.xml
odoo/addons/account_sale_stock_report_non_billed/wizard/__init__.py
odoo/addons/account_sale_stock_report_non_billed/wizard/account_sale_stock_report_non_billed_wiz.py
odoo/addons/account_sale_stock_report_non_billed/wizard/account_sale_stock_report_non_billed_wiz_views.xml
odoo_addon_account_sale_stock_report_non_billed-17.0.1.0.0.2.dist-info/METADATA
odoo_addon_account_sale_stock_report_non_billed-17.0.1.0.0.2.dist-info/WHEEL
odoo_addon_account_sale_stock_report_non_billed-17.0.1.0.0.2.dist-info/top_level.txt
odoo_addon_account_sale_stock_report_non_billed-17.0.1.0.0.2.dist-info/RECORD
